sampleSprider_old/RequestsStudty.py
sampleSprider_old/SampleSprider10_Mayisenlin.py
sampleSprider_old/SampleSprider1_fourClass.py
sampleSprider_old/SampleSprider2_find_all.py
sampleSprider_old/SampleSprider3_Fiction.py
sampleSprider_old/SampleSprider4_Comics.py
sampleSprider_old/SampleSprider4_Comics1.py
sampleSprider_old/SampleSprider5_video.py
sampleSprider_old/SampleSprider6_API.py
sampleSprider_old/SampleSprider7_Selenium.py
sampleSprider_old/SampleSprider7_Selenium1.py
sampleSprider_old/SampleSprider7_Selenium2.py
sampleSprider_old/SampleSprider8_Taobao.py
sampleSprider_old/SampleSprider8_Taobao1.py
sampleSprider_old/SampleSprider8_Taobao2.py
sampleSprider_old/SampleSprider9_Pinduoduo1.py
sampleSprider_old/SampleSprider9_Pinduoduo2.py
sampleSprider_old/SampleSprider9_Pinduoduo3.py
sampleSprider_old/__init__.py
sampleSprider_old/test.py
sampleSprider_old/Common/Info.py
sampleSprider_old/Common/__init__.py
zf_sampleSprider-0.2.0.dist-info/METADATA
zf_sampleSprider-0.2.0.dist-info/WHEEL
zf_sampleSprider-0.2.0.dist-info/entry_points.txt
zf_sampleSprider-0.2.0.dist-info/top_level.txt
zf_sampleSprider-0.2.0.dist-info/RECORD
