Metadata-Version: 2.1
Name: zf-sampleSprider
Version: 0.2.0
Summary: 简易爬虫
Home-page: https://github.com/ilovepythonJAVAc/test2020_8_4
Author: zhangfan
Author-email: 1054934500@qq.com
License: UNKNOWN
Platform: UNKNOWN
Requires-Dist: requests (>=2.25.1)
Requires-Dist: beautifulsoup4 (>=4.9.3)
Requires-Dist: selenium (>=3.141.0)
Requires-Dist: lxml (>=4.6.3)
